{
  "kind": "collectionType",
  "collectionName": "learning_hubs",
  "info": {
    "singularName": "learning-hub",
    "pluralName": "learning-hubs",
    "displayName": "Learning Hub",
    "description": ""
  },
  "options": {
    "draftAndPublish": true
  },
  "attributes": {
    "title": {
      "type": "string"
    },
    "slug": {
      "type": "uid",
      "required": true
    },
    "tags": {
      "type": "string"
    },
    "image": {
      "type": "media",
      "multiple": false,
      "required": false,
      "allowedTypes": [
        "images",
        "files",
        "videos",
        "audios"
      ]
    },
    "learning_hub": {
      "type": "relation",
      "relation": "oneToOne",
      "target": "api::learning-hub-module.learning-hub-module",
      "mappedBy": "learning_hub_module"
    }
  }
}
